URsocket/UR.py
URsocket/__init__.py
URsocket/config.xml
URsocket/robotiq.py
URsocket/rtde.py
URsocket/rtde_config.py
URsocket/serialize.py
URsocket-0.2.dist-info/LICENSE
URsocket-0.2.dist-info/METADATA
URsocket-0.2.dist-info/WHEEL
URsocket-0.2.dist-info/top_level.txt
URsocket-0.2.dist-info/RECORD
