Metadata-Version: 2.1
Name: URsocket
Version: 0.2
Summary: This package is built and tested for universal robot with polyscope version 5.12
Author-email: SarojDebnath <ripandebnath2405@gmail.com>
Project-URL: Homepage, https://github.com/SarojDebnath/URsocket
Classifier: Programming Language :: Python :: 3
Classifier: License :: OSI Approved :: MIT License
Classifier: Operating System :: OS Independent
Requires-Python: >=3.9
License-File: LICENSE
